[{"smjena":"B","datum":"12.9. - 16.9.2022.","prijeposlije":"PRIJE","napomena":"","dezurni":["DEŽURNI PROFESORI",{"name":"SLAVKO FRANJO"},{"name":"ZDRAVKO SABOLEK"},{"name":"NEVEN KOMES"},{"name":"TOMISLAV JAKUPIĆ"},{"name":"ZLATKO DODLEK"}]},["Danijela Vrtiprah",{"name":"2I"},{"name":"2I"},{"name":"1C"},{"name":"2B"},{"name":"2B"},"","",{"name":"2I"},{"name":"2I"},{"name":"2I"},{"name":"1C"},{"name":"1C"},"","","",{"name":"2B"},{"name":"2B"},"",{"name":"1C"},{"name":"1E"},"","","","",{"name":"2A"},{"name":"2A"},"","","","",{"name":"2B"},{"name":"2A"},{"name":"2I"},{"name":"1E"},{"name":"1E"}],["Melita Golubić","","","",{"name":"2D"},{"name":"1G"},{"name":"1G"},{"name":"2D"},{"name":"4A"},{"name":"4A"},{"name":"4B"},{"name":"4B"},{"name":"1G"},"","","",{"name":"2D"},{"name":"2D"},{"name":"4A"},"","","","",{"name":"4B"},{"name":"1G"},{"name":"1G"},{"name":"2D"},{"name":"2D"},{"name":"1I"},{"name":"4A"},"",{"name":"1I"},{"name":"1I"},"","",""],["Petra Sočev Aščić","","","","","","",{"name":"2C"},"","","","","","","","",{"name":"2C"},{"name":"2C"},"",{"name":"2G"},{"name":""},"","","","","","","","",{"name":"2A"},"","",{"name":""},{"name":"2G"},{"name":"2C"},{"name":"2C"}],["Dijana Franjo",{"name":"2D"},{"name":"2D"},{"name":"2I"},{"name":"2I"},"","","","","","","",{"name":"4B","bgColor":"CC9900"},{"name":"4B","bgColor":"CC9900"},{"name":"1I"},{"name":"4B","fontColor":"00B050"},"","","","","","","",{"name":"1G"},{"name":"1I"},{"name":"2D"},{"name":"2I"},{"name":"2I"},{"name":"2D"},{"name":"2D"},{"name":"4A","fontColor":"00B050"},"","",{"name":"4B","bgColor":"CC9900"},{"name":"2G"},{"name":""}],["Sven Tintor",{"name":"2C"},{"name":"2C"},"","","","","",{"name":"2B"},{"name":"2B"},{"name":"2A"},{"name":"2A"},{"name":"4B"},{"name":"4B"},{"name":"4B"},"","","","","","","","","","","","",{"name":"2A"},{"name":"2C"},{"name":"2C"},"",{"name":"4B"},"",{"name":"4B"},{"name":"4A"},{"name":"4A"}],["Blaženka Abramović",{"name":"2CD","bgColor":"00B0F0"},{"name":"2CD","bgColor":"00B0F0"},{"name":"2I","bgColor":"00B0F0"},{"name":"2I","bgColor":"00B0F0"},"","","","","",{"name":"2A","bgColor":"00B0F0"},{"name":"2A","bgColor":"00B0F0"},"",{"name":"1I"},{"name":"1I","bgColor":"00B0F0"},{"name":"2B","fontColor":"00B050"},"","","","","","","","",{"name":"1I","bgColor":"00B0F0"},"",{"name":"2I","bgColor":"00B0F0"},{"name":"2I","bgColor":"00B0F0"},{"name":"2CD","bgColor":"00B0F0"},{"name":"2CD","bgColor":"00B0F0"},{"name":"2A","fontColor":"00B050"},"","","",{"name":"4A","bgColor":"00B0F0"},{"name":"4A","bgColor":"00B0F0"}],["Mia Godek","","","","","","","","","","","","","","","","","","","","","","","","","","","","","","",{"name":"1E"},{"name":"1E","bgColor":"FFFF00"},{"name":"1E","bgColor":"FFFF00"},"",""],["Danijel Kovačić","","","","","","","","","","","","","",{"name":"2B"},"",{"name":"1E"},{"name":"1E"},{"name":"1C"},"",{"name":"2A"},{"name":"2B"},"",{"name":"3E","bgColor":"FFFF00","fontColor":"FF0000"},{"name":"3E","bgColor":"FFFF00","fontColor":"FF0000"},{"name":"3E","bgColor":"FFFF00","fontColor":"FF0000"},{"name":"1I"},{"name":"1I"},{"name":"2A"},{"name":"1C"},"","","","","",""],["Diana Baumkircher","","","","","",{"name":"2B"},{"name":"2A"},"","","","","","","","","","","","","","","","","","","","","","","","","","","",""],["Kristina Babić","","","",{"name":"4B","bgColor":"00FF00"},{"name":"2CD","bgColor":"00FF00"},{"name":"2CD","bgColor":"00FF00"},{"name":"1CE","bgColor":"00FF00"},"","","","","","",{"name":"2G","bgColor":"00FF00"},"","","",{"name":"2B","bgColor":"00B0F0"},{"name":"2A","bgColor":"00B0F0"},{"name":"4A","bgColor":"00B0F0"},{"name":"2I","bgColor":"00B0F0"},{"name":"2I","bgColor":"00B0F0"},"","","","","",{"name":"1G","bgColor":"00FF00"},{"name":"1I","bgColor":"00FF00"},"","","","","",""],["Miroslav Ričko","","","",{"name":"4B"},{"name":"2C"},{"name":"2C"},{"name":"1C"},"","","","","","","","","","",{"name":"2B"},{"name":"2A"},{"name":"4A"},{"name":"2I"},{"name":"2I"},"","","","","",{"name":"1G"},{"name":"1I"},"","","","","",""],["Tereza Kovačić","","","","",{"name":"2D"},{"name":"2D"},{"name":"1E"},"","","","","","",{"name":"2G"},"","","","","","","","","","","","","","","","","","","","",""],["Sandra Krajina","","","","","","","","","","","","","",{"name":"1G"},"","","",{"name":"2G"},{"name":"2D"},{"name":"2C"},{"name":"2C"},{"name":"2D"},{"name":"2D"},{"name":"2D"},"",{"name":"2C"},{"name":"2C"},{"name":"3E","bgColor":"FFFF00","fontColor":"FF0000"},{"name":"3E","bgColor":"FFFF00","fontColor":"FF0000"},"","","","","",{"name":"2G"}],["Ivančica Šurić Pavešić","","","","","",{"name":"2I"},{"name":"2I"},"","","","","",{"name":"2I"},"","","","","","","","","",{"name":"1E","bgColor":"FF99CC"},{"name":"1E","bgColor":"FF99CC"},{"name":"2I"},"",{"name":"4A"},{"name":"4A"},"","","","","","",{"name":""}],["PEDAGOŠKA SLUŽBA",{"name":"1G"},{"name":"1G"},"","","","","","","","","","",{"name":"1G"},"","",{"name":"2G"},{"name":"2G"},{"name":""},"","","","","","","","","","",{"name":"1G"},"",{"name":"2G"},{"name":"2G"},{"name":""},"",""],["Irena Friščić Petrović","","","","","","","",{"name":"2G"},{"name":"2G"},{"name":"2G"},{"name":""},"","","","","","","","","","","","","","","","","","","","","","","",""],["Mario Kiš","","","","","","","","","","","","","","","",{"name":"2A"},{"name":"2A"},{"name":"1E","bgColor":"FFFF00"},{"name":"1E","bgColor":"FFFF00"},{"name":"2B"},"",{"name":"2B"},{"name":"2I"},{"name":"2I"},"","","","","","",{"name":"2I"},{"name":"2I"},{"name":"2B"},{"name":"2B"},{"name":"2B"}],["Ivana Bačani",{"name":"4B"},{"name":"4B"},{"name":"1G"},{"name":"1G"},{"name":"4A"},{"name":"4A"},"",{"name":"4B"},{"name":"1C"},{"name":"4A"},{"name":"1G"},{"name":"1I"},"","","","","","","","",{"name":"4A"},{"name":"4A"},{"name":"1I"},{"name":"4B"},{"name":"4B"},{"name":"4B"},"","","","","",{"name":"1E"},{"name":"1E"},"",""],["Danijel Džambo",{"name":"4A"},{"name":"4A"},{"name":"2B"},"","","","","","","","","","","","",{"name":"4B"},{"name":"4A"},{"name":"2A"},{"name":"4B","bgColor":"CCFFCC"},{"name":"4B","bgColor":"CCFFCC"},{"name":"4B","bgColor":"CCFFCC"},{"name":"4B","bgColor":"CCFFCC"},{"name":"2B","bgColor":"CCFFCC"},{"name":"2B","bgColor":"CCFFCC"},{"name":"2B","bgColor":"CCFFCC"},{"name":"2B","bgColor":"CCFFCC"},{"name":"4B"},"","","","","","","",{"name":"4B"}],["Vladimir Bračko",{"name":"1I","fontColor":"FF0000","pattern":"lightVertical"},{"name":"1I","fontColor":"FF0000","pattern":"lightVertical"},{"name":"2D"},"","","","","","","","","","","","","","","","","","","",{"name":"2A"},{"name":"2A"},"","","","","","",{"name":"2D"},{"name":"2D"},{"name":"2D"},{"name":"2D","pattern":"lightVertical"},{"name":"2D","pattern":"lightVertical"}],["Ištvan Kasaš vježbe i grupe F5","","","","",{"name":"1C"},{"name":"1C"},{"name":"1I","fontColor":"0070C0"},"",{"name":"2C","fontColor":"00B050"},{"name":"1C"},{"name":"1I","fontColor":"00B050"},{"name":"2C","fontColor":"00B050"},{"name":"2C","fontColor":"00B050"},"","","","","","","",{"name":"1I","fontColor":"FF0000"},{"name":"1I","fontColor":"FF0000"},{"name":"2C","fontColor":"00B050"},{"name":"2C","fontColor":"00B050"},{"name":"2C","fontColor":"00B050"},"","","","","","","","","",""],["Marijan Skvaža",{"name":"1C"},{"name":"1C"},"","","","","",{"name":"2D"},{"name":"2C","fontColor":"7030A0"},{"name":"2C","fontColor":"00B050","pattern":"lightVertical"},{"name":"2C","fontColor":"00B050","pattern":"lightVertical"},{"name":"2C","fontColor":"7030A0"},{"name":"2C","fontColor":"7030A0"},{"name":"1C"},"",{"name":"1C"},{"name":"1C"},{"name":"2D"},"","","","",{"name":"2C","fontColor":"7030A0"},{"name":"2C","fontColor":"7030A0"},{"name":"2C","fontColor":"7030A0"},"","","","","",{"name":"2C"},{"name":"2C"},"",{"name":"2D","bgColor":"bee1eb"},{"name":"2D","bgColor":"bee1eb"}],["Krunoslav Kukec","","","","",{"name":"1C"},{"name":"1C"},"",{"name":"1C"},"",{"name":"2C","fontColor":"FF0000"},{"name":"2C","fontColor":"FF0000"},"","","","","","","","","","","","","","","","","","","","","",{"name":"2C"},{"name":"2D"},{"name":"2D"}],["Dubravka Eršetić","","","","","",{"name":"1I","fontColor":"FF0000"},{"name":"1I","fontColor":"FF0000"},"","","","","","","","",{"name":"2I","fontColor":"0070C0","pattern":"lightUp"},{"name":"2I","fontColor":"0070C0","pattern":"lightUp"},{"name":"2I","fontColor":"0070C0","pattern":"lightUp"},{"name":"2I","fontColor":"0070C0","pattern":"lightUp"},"","","","","","","","",{"name":"2I","fontColor":"00B050","pattern":"lightUp"},{"name":"2I","fontColor":"00B050","pattern":"lightUp"},"",{"name":"2A"},{"name":"2B"},{"name":"2A"},{"name":"2I","fontColor":"FF0000","pattern":"lightUp"},{"name":"2I","fontColor":"FF0000","pattern":"lightUp"}],["Zlatko Dodlek","","","","",{"name":"2A","pattern":"lightUp"},{"name":"2A","pattern":"lightUp"},{"name":"4A"},"","","","",{"name":"2A"},{"name":"2A"},"","","","","","","",{"name":"2A","pattern":"lightUp"},{"name":"2A","pattern":"lightUp"},{"name":"4A","bgColor":"CC99FF"},{"name":"4A","bgColor":"CC99FF"},{"name":"4A","bgColor":"CC99FF"},{"name":"4A","bgColor":"CC99FF"},"",{"name":"2I","fontColor":"0070C0"},{"name":"2I","fontColor":"0070C0"},"",{"name":"4A"},{"name":"4A"},{"name":"4A"},{"name":"2I","fontColor":"0070C0"},{"name":"2I","fontColor":"0070C0"}],["Nikola Valentić",{"name":"2B"},{"name":"2B"},{"name":"4A"},{"name":"4A"},{"name":"2A","bgColor":"CC99FF"},{"name":"2A","bgColor":"CC99FF"},"","","",{"name":"2B","bgColor":"CCFFCC"},{"name":"2B","bgColor":"CCFFCC"},{"name":"2B","bgColor":"CCFFCC"},{"name":"2B","bgColor":"CCFFCC"},"","","","","","","",{"name":"2A","bgColor":"404040"},{"name":"2A","bgColor":"404040"},"","","","","","","","","","","","",""],["Miroslav Potroško","","","","","","","","","","","","","","","","","","","","","","",{"name":"4A","bgColor":"404040"},{"name":"4A","bgColor":"404040"},{"name":"4A","bgColor":"404040"},{"name":"4A","bgColor":"404040"},"","","","","","","","",""],["Saša Seretin","","","","","","","","","","","","","","","",{"name":"2I","fontColor":"00B050"},{"name":"2I","fontColor":"00B050"},{"name":"2I","fontColor":"00B050"},{"name":"2I","fontColor":"00B050"},"","","","","","","","","","","","","","","",""],["Zdravko Horvat",{"name":"1I","fontColor":"00B050","pattern":"lightHorizontal"},{"name":"1I","fontColor":"00B050","pattern":"lightHorizontal"},{"name":"1I","fontColor":"00B050","pattern":"lightHorizontal"},{"name":"1I","fontColor":"00B050","pattern":"lightHorizontal"},{"name":"1I","fontColor":"00B050","pattern":"lightHorizontal"},{"name":"1I","fontColor":"00B050","pattern":"lightHorizontal"},{"name":"1I","fontColor":"00B050","pattern":"lightHorizontal"},{"name":"1I","fontColor":"00B050","pattern":"lightHorizontal"},{"name":"1I","fontColor":"00B050","pattern":"lightHorizontal"},{"name":"1I","fontColor":"00B050","pattern":"lightHorizontal"},{"name":"1I","fontColor":"FF0000","pattern":"lightHorizontal"},"","","","",{"name":"1I","fontColor":"00B050","pattern":"lightHorizontal"},{"name":"1I","fontColor":"00B050","pattern":"lightHorizontal"},{"name":"1I","fontColor":"00B050","pattern":"lightHorizontal"},{"name":"1I","fontColor":"00B050","pattern":"lightHorizontal"},{"name":"1I","fontColor":"00B050","pattern":"lightHorizontal"},{"name":"1I","fontColor":"00B050","pattern":"lightHorizontal"},{"name":"1I","fontColor":"00B050","pattern":"lightHorizontal"},"","","","","","","","","","","",{"name":"1I"},{"name":"1I"}],["Neven Komes",{"name":"2A","pattern":"lightUp"},{"name":"2A","pattern":"lightUp"},{"name":"2A","pattern":"lightUp"},{"name":"2A","pattern":"lightUp"},{"name":"1I","fontColor":"FF0000"},"","",{"name":"1I","bgColor":"CC99FF","fontColor":"FF0000"},{"name":"1I","bgColor":"CC99FF","fontColor":"FF0000"},{"name":"1I","bgColor":"CC99FF","fontColor":"FF0000"},{"name":"4A","pattern":"lightUp"},{"name":"4A","pattern":"lightUp"},{"name":"4A","pattern":"lightUp"},{"name":"4A","pattern":"lightUp"},"",{"name":"1I","bgColor":"CC99FF","fontColor":"FF0000"},{"name":"1I","bgColor":"CC99FF","fontColor":"FF0000"},{"name":"1I","bgColor":"CC99FF","fontColor":"FF0000"},{"name":"1I","bgColor":"CC99FF","fontColor":"FF0000"},{"name":"1I","bgColor":"CC99FF","fontColor":"FF0000"},"","","","","","","",{"name":"2I","bgColor":"CC99FF","fontColor":"FF0000"},{"name":"2I","bgColor":"CC99FF","fontColor":"FF0000"},"","","","","",""],["Kristian Solina",{"name":"2A","bgColor":"CC99FF"},{"name":"2A","bgColor":"CC99FF"},{"name":"2A","bgColor":"CC99FF"},{"name":"2A","bgColor":"CC99FF"},"","","","","","",{"name":"4A","bgColor":"CC99FF"},{"name":"4A","bgColor":"CC99FF"},{"name":"4A","bgColor":"CC99FF"},{"name":"4A","bgColor":"CC99FF"},"",{"name":"2I","fontColor":"FF0000"},{"name":"2I","fontColor":"FF0000"},{"name":"2I","fontColor":"FF0000"},{"name":"2I","fontColor":"FF0000"},"","","","",{"name":" "},"","","","","","","","","",{"name":"2I","bgColor":"CC99FF","fontColor":"00B050"},{"name":"2I","bgColor":"CC99FF","fontColor":"00B050"}],["Slavko Franjo",{"name":"4A","bgColor":"FF0000"},{"name":"4A","bgColor":"FF0000"},{"name":"4A","bgColor":"FF0000"},{"name":"4A","bgColor":"FF0000"},{"name":"4B","bgColor":"FF0000"},{"name":"4B","bgColor":"FF0000"},{"name":"2B"},{"name":"2A"},{"name":"2A"},"","","","","","",{"name":"4A"},{"name":"4B"},{"name":"4B","bgColor":"FF0000"},{"name":"2B"},"","","","","","","","","","","","",{"name":"4B"},"",{"name":"2A"},""],["Danijel Mustafa","","","","",{"name":"4B","bgColor":"FFCC00"},{"name":"4B","bgColor":"FFCC00"},{"name":"4B"},"","","","","","","","","","","","","","","","","","","","","","","","","","","",""],["Tomislav Jakupić","","","","","","","","",{"name":"4B"},{"name":"2B","bgColor":"FFCC00"},{"name":"2B","bgColor":"FFCC00"},{"name":"2B","bgColor":"FFCC00"},{"name":"2B","bgColor":"FFCC00"},"","","","",{"name":"4B","bgColor":"FFCC00"},{"name":"4B","bgColor":"FFCC00"},{"name":"4B","bgColor":"FFCC00"},{"name":"4B","bgColor":"FFCC00"},{"name":"4B","bgColor":"FFCC00"},{"name":"2B","bgColor":"FFCC00"},{"name":"2B","bgColor":"FFCC00"},{"name":"2B","bgColor":"FFCC00"},{"name":"2B","bgColor":"FFCC00"},{"name":"2B"},{"name":"4B","bgColor":"FFC000"},{"name":"4B","bgColor":"FFC000"},"","","","","",""],["Iva Horvat",{"name":"3C","bgColor":"CCFFCC","fontColor":"FF0000"},{"name":"3C","bgColor":"CCFFCC","fontColor":"FF0000"},{"name":"3C","bgColor":"CCFFCC","fontColor":"FF0000"},{"name":"3C","bgColor":"CCFFCC","fontColor":"FF0000"},{"name":"3C","bgColor":"CCFFCC","fontColor":"FF0000"},{"name":"3C","bgColor":"CCFFCC","fontColor":"FF0000"},"","","","","","","","","","","","","","","","","","","","","","","","","","","","",""],["Filip Kompari","","",{"name":"1I","bgColor":"262626","fontColor":"FF0000"},{"name":"1I","bgColor":"262626","fontColor":"FF0000"},"","","","","","","","","","","","","","","","","","","","","","","","","","","","","","",""],["Snježana Zrinski","","","","","","","","","","","","","","","","","","","","","","","","","","","","","","","","","","",""],["Dubravka Jakupec","","","","","","","","","","","","","",{"name":"2I"},"","","","","","","","","","",{"name":"4B","bgColor":"FF0000"},{"name":"4B","bgColor":"FF0000"},"",{"name":"4B","bgColor":"FF0000"},{"name":"4B","bgColor":"FF0000"},"","","","","",""],["Kristina Gašparić-Robotić","","","","","","","","","","","","","","","","","","","",{"name":"2G","bgColor":"FFFF00"},{"name":"2G","bgColor":"FFFF00"},{"name":"2G","bgColor":"FFFF00"},"","",{"name":"1E","bgColor":"FF99CC"},{"name":"1E","bgColor":"FF99CC"},{"name":"1E","bgColor":"FF99CC"},"","","","","","","",{"name":"1G","bgColor":"FF99CC"}],["Hrvoje Blažek","","",{"name":"1E","pattern":"lightHorizontal"},{"name":"1E","pattern":"lightHorizontal"},{"name":"1E","pattern":"lightHorizontal"},{"name":"1E","pattern":"lightHorizontal"},"","","","","","",{"name":"1E","pattern":"lightHorizontal"},{"name":"1E","pattern":"lightHorizontal"},"","","","","","","","","","","","","","","","","","","","",""],["Ana Borko",{"name":"1E"},{"name":"1E"},{"name":"1E"},{"name":"1E"},{"name":"1E"},{"name":"1E"},"",{"name":"1E"},{"name":"1E"},{"name":"1E"},{"name":"1E"},{"name":"1E"},{"name":"1E"},{"name":"1E"},"","","",{"name":"1E"},{"name":"1E"},{"name":"2G","pattern":"lightHorizontal"},{"name":"2G","pattern":"lightHorizontal"},{"name":"2G","pattern":"lightHorizontal"},{"name":"1E"},{"name":"1E"},{"name":"1E"},{"name":"1E"},{"name":"1E"},"","","","","","","",""],["Danijel Lovrenčić","","","","","","","",{"name":"1G","pattern":"lightHorizontal"},{"name":"1G","pattern":"lightHorizontal"},{"name":"1G","pattern":"lightHorizontal"},"","","","","","","","","","","","","","","","","","","","","","","","",""],["Neven Nemet","","",{"name":"4B"},{"name":"1C"},{"name":"2I"},"","","","","",{"name":"2I"},{"name":"2I"},{"name":"1C"},{"name":"2A"},"","","","",{"name":"4A"},{"name":"2I"},{"name":"1E"},{"name":"1E"},"","",{"name":"1I"},{"name":"1G"},{"name":"1G"},{"name":"2B"},{"name":"2B"},"","","",{"name":"1I"},{"name":"4B"},{"name":"2A"}],["Melita Jug","","","","","","","","","","","","","","","","","","","","",{"name":"1E"},{"name":"1E"},"","","","","","","","","","","","",""],["","","",{"name":"2C"},{"name":"2C"},"","","","","",{"name":"2D"},{"name":"2D"},{"name":"2G"},{"name":"2G"},{"name":"2C"},"","","","","",{"name":"2D"},{"name":"2D"},{"name":"2C"},"","","","","","","","","","","","",""],["Tanja Brunec   KUH 29",{"name":"1E"},{"name":"1E"},{"name":"1E"},{"name":"1E"},{"name":"1E"},{"name":"1E"},"",{"name":"1E"},{"name":"1E"},{"name":"1E"},{"name":"1E"},{"name":"1E"},{"name":"1E"},{"name":"1E"},"",{"name":"3E","fontColor":"FF0000"},{"name":"3E","fontColor":"FF0000"},{"name":"3E","fontColor":"FF0000"},{"name":"3E","fontColor":"FF0000"},{"name":"3E","fontColor":"FF0000"},{"name":"3E","fontColor":"FF0000"},{"name":"3E","fontColor":"FF0000"},"","","",{"name":"3E","fontColor":"FF0000"},{"name":"3E","fontColor":"FF0000"},{"name":"1E"},{"name":"1E"},"",{"name":"3E","fontColor":"FF0000"},{"name":"3E","fontColor":"FF0000"},{"name":"3E","fontColor":"FF0000"},{"name":"3E","fontColor":"FF0000"},{"name":"3E","fontColor":"FF0000"}],["Ružica Čutanec Splevak KUH 26",{"name":"1E"},{"name":"1E"},"","","","","",{"name":"1E"},{"name":"1E"},{"name":"1E"},{"name":"1E"},{"name":"1E"},"","","","","",{"name":"1E"},{"name":"1E"},"","","",{"name":"1E"},{"name":"1E"},{"name":"1E"},{"name":"1E"},{"name":"1E"},"","","","","","","",""],["Silvija Bago Seretin CVJEĆARSKI","","","","","","","","","","","","","","","","","","",{"name":""},{"name":"2G"},{"name":"2G"},{"name":"2G"},"","","","","","","","","","","","",{"name":"1G"}],["Davorka Đula CVJEĆARSKI",{"name":"2G"},{"name":"2G"},{"name":"2G"},{"name":"2G"},{"name":"2G"},{"name":"2G"},{"name":"2G"},{"name":"1G"},{"name":"1G"},{"name":"1G"},{"name":"2G"},"","","","",{"name":"1G"},{"name":"1G"},{"name":"1G"},{"name":"1G"},{"name":"1G"},{"name":"1G"},{"name":"1G"},{"name":"2G"},{"name":"2G"},{"name":"2G"},{"name":"2G"},{"name":"2G"},{"name":"2G"},{"name":"2G"},"",{"name":"1G"},{"name":"1G"},{"name":"1G"},{"name":"1G"},""],["Zoran Knežević   PEKARSKI 28",{"name":"2G"},{"name":"2G"},{"name":"2G"},{"name":"2G"},{"name":"2G"},{"name":"2G"},{"name":"2G"},"","","","","","","","","","","","","","","",{"name":"2G"},{"name":"2G"},{"name":"2G"},{"name":"2G"},{"name":"2G"},{"name":"2G"},{"name":"2G"},"","","","","",""],["Dijana Zorčić   KUH 30",{"name":"2G"},{"name":"2G"},{"name":"2G"},{"name":"2G"},{"name":"2G"},{"name":"2G"},{"name":"2G"},{"name":"1G"},{"name":"1G"},{"name":"1G"},"","","","","",{"name":"1G"},{"name":"1G"},{"name":"1G"},{"name":"1G"},{"name":"1G"},{"name":"1G"},{"name":"1G"},{"name":"2G"},{"name":"2G"},{"name":"2G"},{"name":"2G"},{"name":"2G"},{"name":"2G"},{"name":"2G"},"",{"name":"1G"},{"name":"1G"},{"name":"1G"},{"name":"1G"},""],["Damir Đelekovčan RUČNA RAD.","","","","","","","","","","","","","","","","","","","",{"name":"1C"},{"name":"1C"},{"name":"1C"},{"name":"1C"},{"name":"1C"},{"name":"1C"},{"name":"1C"},{"name":"1C"},{"name":"1C"},"","",{"name":"1C"},{"name":"1C"},{"name":"1C"},{"name":"1C"},{"name":"1C"}],["Zdravko Sabolek  praksa i grupe F2","","","","","","","",{"name":"2C"},{"name":"2D"},{"name":"2C","fontColor":"002060"},{"name":"2C","fontColor":"002060"},{"name":"2D"},{"name":"2D"},{"name":"2D"},"","","",{"name":"2C"},{"name":"2C"},{"name":"1C"},{"name":"1C"},{"name":"1C"},{"name":"1C"},{"name":"1C"},{"name":"1C"},{"name":"1C"},{"name":"1C"},{"name":"1C"},"","",{"name":"1C"},{"name":"1C"},{"name":"1C"},{"name":"1C"},{"name":"1C"}],["Marko Mihaldinec RAD MSG i S-L","","","","","","","","","","","","","","","",{"name":"1G"},{"name":"1G"},{"name":"1G"},{"name":"1G"},{"name":"1G"},{"name":"1G"},{"name":"1G"},"","","","","","","","",{"name":"1G"},{"name":"1G"},{"name":"1G"},{"name":"1G"},{"name":"1G"}],["Igor Sraček RUČ.RAD.",{"name":"1I","fontColor":"0070C0","pattern":"lightHorizontal"},{"name":"1I","fontColor":"0070C0","pattern":"lightHorizontal"},{"name":"1I","fontColor":"0070C0","pattern":"lightHorizontal"},{"name":"1I","fontColor":"0070C0","pattern":"lightHorizontal"},{"name":"1I","fontColor":"0070C0","pattern":"lightHorizontal"},{"name":"1I","fontColor":"0070C0","pattern":"lightHorizontal"},"",{"name":"1I","fontColor":"0070C0","pattern":"lightHorizontal"},{"name":"1I","fontColor":"0070C0","pattern":"lightHorizontal"},{"name":"1I","fontColor":"0070C0","pattern":"lightHorizontal"},{"name":"1I","fontColor":"0070C0","pattern":"lightHorizontal"},"","","","",{"name":"1I","fontColor":"0070C0","pattern":"lightHorizontal"},{"name":"1I","fontColor":"0070C0","pattern":"lightHorizontal"},{"name":"1I","fontColor":"0070C0","pattern":"lightHorizontal"},{"name":"1I","fontColor":"0070C0","pattern":"lightHorizontal"},{"name":"1I","fontColor":"0070C0","pattern":"lightHorizontal"},{"name":"1I","fontColor":"0070C0","pattern":"lightHorizontal"},{"name":"1I","fontColor":"0070C0","pattern":"lightHorizontal"},{"name":"3I","fontColor":"FF0000","pattern":"lightHorizontal"},{"name":"3I","fontColor":"FF0000","pattern":"lightHorizontal"},{"name":"3I","fontColor":"FF0000","pattern":"lightHorizontal"},{"name":"3I","fontColor":"FF0000","pattern":"lightHorizontal"},{"name":"3I","fontColor":"FF0000","pattern":"lightHorizontal"},{"name":"3I","fontColor":"FF0000","pattern":"lightHorizontal"},{"name":"3I","fontColor":"FF0000","pattern":"lightHorizontal"},"",{"name":"3I","fontColor":"FF0000","pattern":"lightHorizontal"},{"name":"3I","fontColor":"FF0000","pattern":"lightHorizontal"},{"name":"3I","fontColor":"FF0000","pattern":"lightHorizontal"},{"name":"3I","fontColor":"FF0000","pattern":"lightHorizontal"},{"name":"3I","fontColor":"FF0000","pattern":"lightHorizontal"}],["DEŽURNI PROFESORI",{"name":"SLAVKO FRANJO"},"","","","","","",{"name":"ZDRAVKO SABOLEK"},"","","","","","","",{"name":"NEVEN KOMES"},"","","","","","",{"name":"TOMISLAV JAKUPIĆ"},"","","","","","","",{"name":"ZLATKO DODLEK"},"","","",""]]